stacksort/__init__.py
stacksort/_meta/__init__.py
stacksort/_meta/compile.py
stacksort/_meta/injector.py
stacksort/_meta/stackoverflow/__init__.py
stacksort/_meta/stackoverflow/find.py
stacksort-0.1.0.dist-info/LICENSE
stacksort-0.1.0.dist-info/METADATA
stacksort-0.1.0.dist-info/WHEEL
stacksort-0.1.0.dist-info/top_level.txt
stacksort-0.1.0.dist-info/RECORD
