Metadata-Version: 2.1
Name: stacksort
Version: 0.1.0
Summary: UNKNOWN
Home-page: UNKNOWN
Author: David Buckley <david@davidbuckley.ca
License: UNKNOWN
Platform: UNKNOWN
Requires-Dist: stackapi
Requires-Dist: lxml
Requires-Dist: bs4
